Pipeline_processor.v
// Modified version of a pipelined MIPS32 processor
// Adapted to be a personalized implementation

module myPipeMIPS32 (clk1, clk2);

    input clk1, clk2;  // Two-phase clock input

    reg [31:0] PC, IF_ID_IR, IF_ID_NPC;
    reg [31:0] ID_EX_IR, ID_EX_NPC, ID_EX_A, ID_EX_B, ID_EX_Imm;
    reg [2:0]  ID_EX_type, EX_MEM_type, MEM_WB_type;
    reg [31:0] EX_MEM_IR, EX_MEM_ALUOut, EX_MEM_B;
    reg        EX_MEM_cond;
    reg [31:0] MEM_WB_IR, MEM_WB_ALUOut, MEM_WB_LMD;

    reg [31:0] Reg [0:31];  // Register File
    reg [31:0] Mem [0:1023];  // Main Memory

    // Opcode Definitions
    parameter ADD=6'b000000, SUB=6'b000001, AND=6'b000010, OR=6'b000011, SLT=6'b000100;
    parameter MUL=6'b000101, HLT=6'b111111, LW=6'b001000, SW=6'b00101, ADDI=6'b001010;
    parameter SUBI=6'b001011, SLTI=6'b001100, BNEQZ=6'b001101, BEQZ=6'b001110;

    // Stage Types
    parameter RR_ALU=3'b000, RM_ALU=3'b001, LOAD=3'b010, STORE=3'b011;
    parameter BRANCH=3'b100, HALT=3'b101;

    reg HALTED;  // Indicates HLT has executed
    reg TAKEN_BRANCH;  // Prevents writes on branch

    // Instruction Fetch Stage
    always @(posedge clk1)
        if (!HALTED) begin
            if (((EX_MEM_IR[31:26] == BEQZ) && (EX_MEM_cond == 1)) ||
                ((EX_MEM_IR[31:26] == BNEQZ) && (EX_MEM_cond == 0))) begin
                IF_ID_IR <= #2 Mem[EX_MEM_ALUOut];
                TAKEN_BRANCH <= #2 1;
                IF_ID_NPC <= #2 EX_MEM_ALUOut + 1;
                PC <= #2 EX_MEM_ALUOut + 1;
            end else begin
                IF_ID_IR <= #2 Mem[PC];
                IF_ID_NPC <= #2 PC + 1;
                PC <= #2 PC + 1;
            end
        end

    // Instruction Decode Stage
    always @(posedge clk2)
        if (!HALTED) begin
            ID_EX_A <= #2 (IF_ID_IR[25:21] == 0) ? 0 : Reg[IF_ID_IR[25:21]];
            ID_EX_B <= #2 (IF_ID_IR[20:16] == 0) ? 0 : Reg[IF_ID_IR[20:16]];
            ID_EX_NPC <= #2 IF_ID_NPC;
            ID_EX_IR <= #2 IF_ID_IR;
            ID_EX_Imm <= #2 {{16{IF_ID_IR[15]}}, IF_ID_IR[15:0]};

            case (IF_ID_IR[31:26])
                ADD, SUB, MUL, AND, OR, SLT: ID_EX_type <= #2 RR_ALU;
                ADDI, SUBI, SLTI: ID_EX_type <= #2 RM_ALU;
                LW: ID_EX_type <= #2 LOAD;
                SW: ID_EX_type <= #2 STORE;
                BNEQZ, BEQZ: ID_EX_type <= #2 BRANCH;
                HLT: ID_EX_type <= #2 HALT;
                default: ID_EX_type <= #2 HALT;
            endcase
        end

    // Execution Stage
    always @(posedge clk1)
        if (!HALTED) begin
            EX_MEM_type <= #2 ID_EX_type;
            EX_MEM_IR <= #2 ID_EX_IR;
            TAKEN_BRANCH <= #2 0;

            case (ID_EX_type)
                RR_ALU: case (ID_EX_IR[31:26])
                    ADD: EX_MEM_ALUOut <= #2 ID_EX_A + ID_EX_B;
                    SUB: EX_MEM_ALUOut <= #2 ID_EX_A - ID_EX_B;
                    MUL: EX_MEM_ALUOut <= #2 ID_EX_A * ID_EX_B;
                    OR:  EX_MEM_ALUOut <= #2 ID_EX_A | ID_EX_B;
                    AND: EX_MEM_ALUOut <= #2 ID_EX_A & ID_EX_B;
                    SLT: EX_MEM_ALUOut <= #2 (ID_EX_A < ID_EX_B);
                    default: EX_MEM_ALUOut <= #2 32'hxxxxxxxx;
                endcase

                RM_ALU: case (ID_EX_IR[31:26])
                    ADDI: EX_MEM_ALUOut <= #2 ID_EX_A + ID_EX_Imm;
                    SUBI: EX_MEM_ALUOut <= #2 ID_EX_A - ID_EX_Imm;
                    SLTI: EX_MEM_ALUOut <= #2 (ID_EX_A < ID_EX_Imm);
                    default: EX_MEM_ALUOut <= #2 32'hxxxxxxxx;
                endcase

                LOAD, STORE: begin
                    EX_MEM_ALUOut <= #2 ID_EX_A + ID_EX_Imm;
                    EX_MEM_B <= #2 ID_EX_B;
                end

                BRANCH: begin
                    EX_MEM_ALUOut <= #2 ID_EX_NPC + ID_EX_Imm;
                    EX_MEM_cond <= #2 (ID_EX_A == 0);
                end
            endcase
        end

    // Memory Access Stage
    always @(posedge clk2)
        if (!HALTED) begin
            MEM_WB_type <= #2 EX_MEM_type;
            MEM_WB_IR <= #2 EX_MEM_IR;

            case (EX_MEM_type)
                RR_ALU, RM_ALU:
                    MEM_WB_ALUOut <= #2 EX_MEM_ALUOut;
                LOAD:
                    MEM_WB_LMD <= #2 Mem[EX_MEM_ALUOut];
                STORE:
                    if (!TAKEN_BRANCH)
                        Mem[EX_MEM_ALUOut] <= #2 EX_MEM_B;
            endcase
        end

    // Write-Back Stage
    always @(posedge clk1)
        if (!TAKEN_BRANCH) begin
            case (MEM_WB_type)
                RR_ALU:
                    Reg[MEM_WB_IR[15:11]] <= #2 MEM_WB_ALUOut;
                RM_ALU:
                    Reg[MEM_WB_IR[20:16]] <= #2 MEM_WB_ALUOut;
                LOAD:
                    Reg[MEM_WB_IR[20:16]] <= #2 MEM_WB_LMD;
                HALT:
                    HALTED <= #2 1;
            endcase
        end

endmodule

processor_sort.v
module tb;

    reg clk1, clk2;

    // ---------------- CLOCK GENERATION ----------------
    initial begin 
        clk1 = 1'b0;
        clk2 = 1'b0;
    end

    // Two-phase clock: clk1 leads, clk2 follows
    always begin
        #5 clk1 = 1'b1; #5 clk1 = 1'b0;
        #5 clk2 = 1'b1; #5 clk2 = 1'b0;
    end

    // ---------------- DUT INSTANTIATION ----------------
    myPipeMIPS32 dut (clk1, clk2);

    // ---------------- INITIALIZATION & PROGRAM ----------------
    initial begin
        // Reset Control Signals
        dut.HALTED = 0;
        dut.TAKEN_BRANCH = 0;
        dut.PC = 0;

        // -------- DATA INITIALIZATION (Mem[100] to Mem[119]) --------
        // Initializing with a descending sequence to test worst-case sorting
        dut.Mem[100] = 20; dut.Mem[101] = 19; dut.Mem[102] = 18; dut.Mem[103] = 17;
        dut.Mem[104] = 16; dut.Mem[105] = 15; dut.Mem[106] = 14; dut.Mem[107] = 13;
        dut.Mem[108] = 12; dut.Mem[109] = 11; dut.Mem[110] = 10; dut.Mem[111] = 9;
        dut.Mem[112] = 8;  dut.Mem[113] = 7;  dut.Mem[114] = 6;  dut.Mem[115] = 5;
        dut.Mem[116] = 4;  dut.Mem[117] = 3;  dut.Mem[118] = 2;  dut.Mem[119] = 1;

        // -------- MACHINE CODE PROGRAM --------
        // Note: 3 NOPs (0x0C000000 or 0x0) are required between a 
        // destination register write and a source register read.

        // [0-3] Setup: R7 = 20 (Size), R3 = 100 (Base Address)
        dut.Mem[0]  = 32'h28070014; // ADDI R7, R0, 20
        dut.Mem[1]  = 32'h28030064; // ADDI R3, R0, 100
        dut.Mem[2]  = 32'h00000000; // NOP
        dut.Mem[3]  = 32'h00000000; // NOP

        // [4-7] Outer Loop Init: R1 = 0
        dut.Mem[4]  = 32'h28210000; // ADDI R1, R0, 0   <-- OUTER_LOOP_START
        dut.Mem[5]  = 32'h00000000; // NOP
        dut.Mem[6]  = 32'h00000000; // NOP
        dut.Mem[7]  = 32'h00000000; // NOP

        // [8-11] Inner Loop Init: R2 = 0
        dut.Mem[8]  = 32'h28020000; // ADDI R2, R0, 0   <-- INNER_LOOP_START
        dut.Mem[9]  = 32'h00000000; // NOP
        dut.Mem[10] = 32'h00000000; // NOP
        dut.Mem[11] = 32'h00000000; // NOP

        // [12-15] Calculate Address: R10 = Base + j
        dut.Mem[12] = 32'h00625000; // ADD  R10, R3, R2
        dut.Mem[13] = 32'h00000000; // NOP
        dut.Mem[14] = 32'h00000000; // NOP
        dut.Mem[15] = 32'h00000000; // NOP

        // [16-20] Load elements: R5 = Mem[j], R6 = Mem[j+1]
        dut.Mem[16] = 32'h21450000; // LW   R5, 0(R10)
        dut.Mem[17] = 32'h21460001; // LW   R6, 1(R10)
        dut.Mem[18] = 32'h00000000; // NOP
        dut.Mem[19] = 32'h00000000; // NOP
        dut.Mem[20] = 32'h00000000; // NOP

        // [21-24] Comparison: R9 = (R6 < R5)
        dut.Mem[21] = 32'h10C54800; // SLT  R9, R6, R5
        dut.Mem[22] = 32'h00000000; // NOP
        dut.Mem[23] = 32'h00000000; // NOP
        dut.Mem[24] = 32'h00000000; // NOP

        // [25-26] Branch if No Swap needed: if R9==0 skip to [30]
        // Offset: Target(30) - NPC(26) = 4
        dut.Mem[25] = 32'h39200004; // BEQZ R9, 4
        dut.Mem[26] = 32'h00000000; // NOP (Branch Delay Slot)

        // [27-29] Swap Elements
        dut.Mem[27] = 32'h15460000; // SW   R6, 0(R10)
        dut.Mem[28] = 32'h15450001; // SW   R5, 1(R10)
        dut.Mem[29] = 32'h00000000; // NOP

        // [30-33] Increment Inner Loop: j = j + 1
        dut.Mem[30] = 32'h28420001; // ADDI R2, R2, 1
        dut.Mem[31] = 32'h00000000; // NOP
        dut.Mem[32] = 32'h00000000; // NOP
        dut.Mem[33] = 32'h00000000; // NOP

        // [34-37] Check Inner Loop Condition: R9 = (20 - 1 - j)
        // For simplicity, we compare j against (Size - 1)
        dut.Mem[34] = 32'h28E9FFFF; // ADDI R9, R7, -1 (R9 = 19)
        dut.Mem[35] = 32'h00000000; // NOP
        dut.Mem[36] = 32'h04494800; // SUB  R9, R9, R2 (R9 = 19 - j)
        dut.Mem[37] = 32'h00000000; // NOP

        // [38-39] Inner Loop Branch: if R9 != 0 back to [12]
        // Offset: Target(12) - NPC(39) = -27 (0xFFE5)
        dut.Mem[38] = 32'h3520FFE5; // BNEQZ R9, -27
        dut.Mem[39] = 32'h00000000; // NOP (Branch Delay Slot)

        // [40-43] Increment Outer Loop: i = i + 1
        dut.Mem[40] = 32'h28210001; // ADDI R1, R1, 1
        dut.Mem[41] = 32'h00000000; // NOP
        dut.Mem[42] = 32'h00000000; // NOP
        dut.Mem[43] = 32'h00000000; // NOP

        // [44-47] Check Outer Loop Condition: R9 = (20 - i)
        dut.Mem[44] = 32'h04274800; // SUB  R9, R7, R1
        dut.Mem[45] = 32'h00000000; // NOP
        dut.Mem[46] = 32'h00000000; // NOP
        dut.Mem[47] = 32'h00000000; // NOP

        // [48-49] Outer Loop Branch: if R9 != 0 back to [8]
        // Offset: Target(8) - NPC(49) = -41 (0xFFD7)
        dut.Mem[48] = 32'h3520FFD7; // BNEQZ R9, -41
        dut.Mem[49] = 32'h00000000; // NOP (Branch Delay Slot)

        // [50] Finish
        dut.Mem[50] = 32'hFC000000; // HLT
    end

    // ---------------- WAVEFORM & MONITORING ----------------
    initial begin 
        $dumpfile("bubble_sort.vcd");
        $dumpvars(0, dut);
    end

    initial begin
        // The sorting of 20 numbers takes thousands of cycles
        // Adjust timeout if necessary
        #500000; 
        if (!dut.HALTED) begin
            $display("Simulation Timed Out!");
            $finish;
        end
    end

    initial begin
        wait(dut.HALTED == 1);
        #100; // Final buffer

        $display("\n================================================");
        $display("       BUBBLE SORT COMPLETED SUCCESSFULLY       ");
        $display("================================================\n");

        for (integer i = 0; i < 4; i = i + 1) begin
            $display("Mem[%0d-%0d]: %3d %3d %3d %3d %3d", 
                100 + (i*5), 104 + (i*5),
                dut.Mem[100 + (i*5)], dut.Mem[101 + (i*5)], 
                dut.Mem[102 + (i*5)], dut.Mem[103 + (i*5)], 
                dut.Mem[104 + (i*5)]);
        end

        $display("\n================================================");
        $finish;
    end

endmodule

bubble_sort.vcd
$date
	Wed Jan 21 23:30:34 2026
$end
$version
	Icarus Verilog
$end
$timescale
	1s
$end
$scope module tb $end
$scope module dut $end
$var wire 1 ! clk1 $end
$var wire 1 " clk2 $end
$var parameter 6 # ADD $end
$var parameter 6 $ ADDI $end
$var parameter 6 % AND $end
$var parameter 6 & BEQZ $end
$var parameter 6 ' BNEQZ $end
$var parameter 3 ( BRANCH $end
$var parameter 3 ) HALT $end
$var parameter 6 * HLT $end
$var parameter 3 + LOAD $end
$var parameter 6 , LW $end
$var parameter 6 - MUL $end
$var parameter 6 . OR $end
$var parameter 3 / RM_ALU $end
$var parameter 3 0 RR_ALU $end
$var parameter 6 1 SLT $end
$var parameter 6 2 SLTI $end
$var parameter 3 3 STORE $end
$var parameter 6 4 SUB $end
$var parameter 6 5 SUBI $end
$var parameter 6 6 SW $end
$var reg 32 7 EX_MEM_ALUOut [31:0] $end
$var reg 32 8 EX_MEM_B [31:0] $end
$var reg 32 9 EX_MEM_IR [31:0] $end
$var reg 1 : EX_MEM_cond $end
$var reg 3 ; EX_MEM_type [2:0] $end
$var reg 1 < HALTED $end
$var reg 32 = ID_EX_A [31:0] $end
$var reg 32 > ID_EX_B [31:0] $end
$var reg 32 ? ID_EX_IR [31:0] $end
$var reg 32 @ ID_EX_Imm [31:0] $end
$var reg 32 A ID_EX_NPC [31:0] $end
$var reg 3 B ID_EX_type [2:0] $end
$var reg 32 C IF_ID_IR [31:0] $end
$var reg 32 D IF_ID_NPC [31:0] $end
$var reg 32 E MEM_WB_ALUOut [31:0] $end
$var reg 32 F MEM_WB_IR [31:0] $end
$var reg 32 G MEM_WB_LMD [31:0] $end
$var reg 3 H MEM_WB_type [2:0] $end
$var reg 32 I PC [31:0] $end
$var reg 1 J TAKEN_BRANCH $end
$upscope $end
$upscope $end
$enddefinitions $end
$comment Show the parameter values. $end
$dumpall
b1001 6
b1011 5
b1 4
b11 3
b1100 2
b100 1
b0 0
b1 /
b11 .
b101 -
b1000 ,
b10 +
b111111 *
b101 )
b100 (
b1101 '
b1110 &
b10 %
b1010 $
b0 #
$end
#0
$dumpvars
0J
b0 I
bx H
bx G
bx F
bx E
bx D
bx C
bx B
bx A
bx @
bx ?
bx >
bx =
0<
bx ;
x:
bx 9
bx 8
bx 7
0"
0!
$end
#5
1!
#7
b1 I
b1 D
b101000000001110000000000010100 C
#10
0!
#15
1"
#17
b1 B
b10100 @
b101000000001110000000000010100 ?
b1 A
b0 =
#20
0"
#25
1!
#27
b10100 7
b101000000001110000000000010100 9
b1 ;
b10 I
b10 D
b101000000000110000000001100100 C
#30
0!
#35
1"
#37
b10100 E
b101000000001110000000000010100 F
b1 H
b1100100 @
b101000000000110000000001100100 ?
b10 A
#40
0"
#45
1!
#47
b11 I
b11 D
b0 C
b1100100 7
b101000000000110000000001100100 9
#50
0!
#55
1"
#57
b0 B
b0 @
b0 ?
b11 A
b0 >
b1100100 E
b101000000000110000000001100100 F
#60
0"
#65
1!
#67
b0 7
b0 9
b0 ;
b100 I
b100 D
#70
0!
#75
1"
#77
b0 E
b0 F
b0 H
b100 A
#80
0"
#85
1!
#87
b101 I
b101 D
b101000001000010000000000000000 C
#90
0!
#95
1"
#97
b1 B
b101000001000010000000000000000 ?
b101 A
bx >
bx =
#100
0"
#105
1!
#107
bx 7
b101000001000010000000000000000 9
b1 ;
b110 I
b110 D
b0 C
#110
0!
#115
1"
#117
bx E
b101000001000010000000000000000 F
b1 H
b0 B
b0 ?
b110 A
b0 >
b0 =
#120
0"
#125
1!
#127
b111 I
b111 D
b0 7
b0 9
b0 ;
#130
0!
#135
1"
#137
b111 A
b0 E
b0 F
b0 H
#140
0"
#145
1!
#147
b1000 I
b1000 D
#150
0!
#155
1"
#157
b1000 A
#160
0"
#165
1!
#167
b1001 I
b1001 D
b101000000000100000000000000000 C
#170
0!
#175
1"
#177
b1 B
b101000000000100000000000000000 ?
b1001 A
bx >
#180
0"
#185
1!
#187
b101000000000100000000000000000 9
b1 ;
b1010 I
b1010 D
b0 C
#190
0!
#195
1"
#197
b101000000000100000000000000000 F
b1 H
b0 B
b0 ?
b1010 A
b0 >
#200
0"
#205
1!
#207
b1011 I
b1011 D
b0 9
b0 ;
#210
0!
#215
1"
#217
b1011 A
b0 F
b0 H
#220
0"
#225
1!
#227
b1100 I
b1100 D
#230
0!
#235
1"
#237
b1100 A
#240
0"
#245
1!
#247
b1101 I
b1101 D
b11000100101000000000000 C
#250
0!
#255
1"
#257
b101000000000000 @
b11000100101000000000000 ?
b1101 A
b1100100 =
#260
0"
#265
1!
#267
b1100100 7
b11000100101000000000000 9
b1110 I
b1110 D
b0 C
#270
0!
#275
1"
#277
b1100100 E
b11000100101000000000000 F
b0 @
b0 ?
b1110 A
b0 =
#280
0"
#285
1!
#287
b1111 I
b1111 D
b0 7
b0 9
#290
0!
#295
1"
#297
b1111 A
b0 E
b0 F
#300
0"
#305
1!
#307
b10000 I
b10000 D
#310
0!
#315
1"
#317
b10000 A
#320
0"
#325
1!
#327
b10001 I
b10001 D
b100001010001010000000000000000 C
#330
0!
#335
1"
#337
b10 B
b100001010001010000000000000000 ?
b10001 A
bx >
b1100100 =
#340
0"
#345
1!
#347
b1100100 7
b100001010001010000000000000000 9
b10 ;
b10010 I
b10010 D
b100001010001100000000000000001 C
#350
0!
#355
1"
#357
b10100 G
b100001010001010000000000000000 F
b10 H
b1 @
b100001010001100000000000000001 ?
b10010 A
#360
0"
#365
1!
#367
b10011 I
b10011 D
b0 C
b1100101 7
b100001010001100000000000000001 9
#370
0!
#375
1"
#377
b0 B
b0 @
b0 ?
b10011 A
b0 >
b0 =
b10011 G
b100001010001100000000000000001 F
#380
0"
#385
1!
#387
b0 7
b0 9
b0 ;
b10100 I
b10100 D
#390
0!
#395
1"
#397
b0 F
b0 H
b10100 A
#400
0"
#405
1!
#407
b10101 I
b10101 D
#410
0!
#415
1"
#417
b10101 A
#420
0"
#425
1!
#427
b10110 I
b10110 D
b10000110001010100100000000000 C
#430
0!
#435
1"
#437
b100100000000000 @
b10000110001010100100000000000 ?
b10110 A
b10100 >
b10011 =
#440
0"
#445
1!
#447
b10111 I
b10111 D
b0 C
b1 7
b10000110001010100100000000000 9
#450
0!
#455
1"
#457
b0 @
b0 ?
b10111 A
b0 >
b0 =
b1 E
b10000110001010100100000000000 F
#460
0"
#465
1!
#467
b0 7
b0 9
b11000 I
b11000 D
#470
0!
#475
1"
#477
b0 E
b0 F
b11000 A
#480
0"
#485
1!
#487
b11001 I
b11001 D
#490
0!
#495
1"
#497
b11001 A
#500
0"
#505
1!
#507
b11010 I
b11010 D
b111001001000000000000000000100 C
#510
0!
#515
1"
#517
b100 B
b100 @
b111001001000000000000000000100 ?
b11010 A
b1 =
#520
0"
#525
1!
#527
b11011 I
b11011 D
b0 C
0:
b11110 7
b111001001000000000000000000100 9
b100 ;
#530
0!
#535
1"
#537
b0 B
b0 @
b0 ?
b11011 A
b0 =
b111001001000000000000000000100 F
b100 H
#540
0"
#545
1!
#547
b0 7
b0 9
b0 ;
b11100 I
b11100 D
b10101010001100000000000000000 C
#550
0!
#555
1"
#557
b0 F
b0 H
b10101010001100000000000000000 ?
b11100 A
b10011 >
b1100100 =
#560
0"
#565
1!
#567
b11101 I
b11101 D
b10101010001010000000000000001 C
b11101101100 7
b10101010001100000000000000000 9
#570
0!
#575
1"
#577
b1 @
b10101010001010000000000000001 ?
b11101 A
b10100 >
b11101101100 E
b10101010001100000000000000000 F
#580
0"
#585
1!
#587
b11111010000 7
b10101010001010000000000000001 9
b11110 I
b11110 D
b0 C
#590
0!
#595
1"
#597
b11111010000 E
b10101010001010000000000000001 F
b0 @
b0 ?
b11110 A
b0 >
b0 =
#600
0"
#605
1!
#607
b11111 I
b11111 D
b101000010000100000000000000001 C
b0 7
b0 9
#610
0!
#615
1"
#617
b1 B
b1 @
b101000010000100000000000000001 ?
b11111 A
b0 E
b0 F
#620
0"
#625
1!
#627
b1 7
b101000010000100000000000000001 9
b1 ;
b100000 I
b100000 D
b0 C
#630
0!
#635
1"
#637
b1 E
b101000010000100000000000000001 F
b1 H
b0 B
b0 @
b0 ?
b100000 A
#640
0"
#645
1!
#647
b100001 I
b100001 D
b0 7
b0 9
b0 ;
#650
0!
#655
1"
#657
b100001 A
b0 E
b0 F
b0 H
#660
0"
#665
1!
#667
b100010 I
b100010 D
#670
0!
#675
1"
#677
b100010 A
#680
0"
#685
1!
#687
b100011 I
b100011 D
b101000111010011111111111111111 C
#690
0!
#695
1"
#697
b1 B
b11111111111111111111111111111111 @
b101000111010011111111111111111 ?
b100011 A
b1 >
b10100 =
#700
0"
#705
1!
#707
b10011 7
b101000111010011111111111111111 9
b1 ;
b100100 I
b100100 D
b0 C
#710
0!
#715
1"
#717
b10011 E
b101000111010011111111111111111 F
b1 H
b0 B
b0 @
b0 ?
b100100 A
b0 >
b0 =
#720
0"
#725
1!
#727
b100101 I
b100101 D
b100010010010100100000000000 C
b0 7
b0 9
b0 ;
#730
0!
#735
1"
#737
b100100000000000 @
b100010010010100100000000000 ?
b100101 A
b10011 >
b1 =
b0 E
b0 F
b0 H
#740
0"
#745
1!
#747
b11111111111111111111111111101110 7
b100010010010100100000000000 9
b100110 I
b100110 D
b0 C
#750
0!
#755
1"
#757
b11111111111111111111111111101110 E
b100010010010100100000000000 F
b0 @
b0 ?
b100110 A
b0 >
b0 =
#760
0"
#765
1!
#767
b100111 I
b100111 D
b110101001000001111111111100101 C
b0 7
b0 9
#770
0!
#775
1"
#777
b100 B
b11111111111111111111111111100101 @
b110101001000001111111111100101 ?
b100111 A
b11111111111111111111111111101110 =
b0 E
b0 F
#780
0"
#785
1!
#787
b1100 7
b110101001000001111111111100101 9
b100 ;
b101000 I
b101000 D
b0 C
#790
0!
#795
1"
#797
b110101001000001111111111100101 F
b100 H
b0 B
b0 @
b0 ?
b101000 A
b0 =
#800
0"
#805
1!
#807
b1101 I
b1101 D
1J
b11000100101000000000000 C
b0 7
b0 9
b0 ;
#810
0!
#815
1"
#817
b101000000000000 @
b11000100101000000000000 ?
b1101 A
b1 >
b1100100 =
b0 F
b0 H
#820
0"
#825
1!
#827
b1100101 7
0J
b11000100101000000000000 9
b1110 I
b1110 D
b0 C
#830
0!
#835
1"
#837
b1100101 E
b11000100101000000000000 F
b0 @
b0 ?
b1110 A
b0 >
b0 =
#840
0"
#845
1!
#847
b1111 I
b1111 D
b0 7
b0 9
#850
0!
#855
1"
#857
b1111 A
b0 E
b0 F
#860
0"
#865
1!
#867
b10000 I
b10000 D
#870
0!
#875
1"
#877
b10000 A
#880
0"
#885
1!
#887
b10001 I
b10001 D
b100001010001010000000000000000 C
#890
0!
#895
1"
#897
b10 B
b100001010001010000000000000000 ?
b10001 A
b10100 >
b1100101 =
#900
0"
#905
1!
#907
b10100 8
b1100101 7
b100001010001010000000000000000 9
b10 ;
b10010 I
b10010 D
b100001010001100000000000000001 C
#910
0!
#915
1"
#917
b100001010001010000000000000000 F
b10 H
b1 @
b100001010001100000000000000001 ?
b10010 A
b10011 >
#920
0"
#925
1!
#927
b10011 I
b10011 D
b0 C
b10011 8
b1100110 7
b100001010001100000000000000001 9
#930
0!
#935
1"
#937
b0 B
b0 @
b0 ?
b10011 A
b0 >
b0 =
b10010 G
b100001010001100000000000000001 F
#940
0"
#945
1!
#947
b0 7
b0 9
b0 ;
b10100 I
b10100 D
#950
0!
#955
1"
#957
b0 F
b0 H
b10100 A
#960
0"
#965
1!
#967
b10101 I
b10101 D
#970
0!
#975
1"
#977
b10101 A
#980
0"
#985
1!
#987
b10110 I
b10110 D
b10000110001010100100000000000 C
#990
0!
#995
1"
#997
b100100000000000 @
b10000110001010100100000000000 ?
b10110 A
b10011 >
b10010 =
#1000
0"
#1005
1!
#1007
b10111 I
b10111 D
b0 C
b1 7
b10000110001010100100000000000 9
#1010
0!
#1015
1"
#1017
b0 @
b0 ?
b10111 A
b0 >
b0 =
b1 E
b10000110001010100100000000000 F
#1020
0"
#1025
1!
#1027
b0 7
b0 9
b11000 I
b11000 D
#1030
0!
#1035
1"
#1037
b0 E
b0 F
b11000 A
#1040
0"
#1045
1!
#1047
b11001 I
b11001 D
#1050
0!
#1055
1"
#1057
b11001 A
#1060
0"
#1065
1!
#1067
b11010 I
b11010 D
b111001001000000000000000000100 C
#1070
0!
#1075
1"
#1077
b100 B
b100 @
b111001001000000000000000000100 ?
b11010 A
b1 =
#1080
0"
#1085
1!
#1087
b11011 I
b11011 D
b0 C
b11110 7
b111001001000000000000000000100 9
b100 ;
#1090
0!
#1095
1"
#1097
b0 B
b0 @
b0 ?
b11011 A
b0 =
b111001001000000000000000000100 F
b100 H
#1100
0"
#1105
1!
#1107
b0 7
b0 9
b0 ;
b11100 I
b11100 D
b10101010001100000000000000000 C
#1110
0!
#1115
1"
#1117
b0 F
b0 H
b10101010001100000000000000000 ?
b11100 A
b10010 >
b1100101 =
#1120
0"
#1125
1!
#1127
b11101 I
b11101 D
b10101010001010000000000000001 C
b11100011010 7
b10101010001100000000000000000 9
#1130
0!
#1135
1"
#1137
b1 @
b10101010001010000000000000001 ?
b11101 A
b10011 >
b11100011010 E
b10101010001100000000000000000 F
#1140
0"
#1145
1!
#1147
b11101111111 7
b10101010001010000000000000001 9
b11110 I
b11110 D
b0 C
#1150
0!
#1155
1"
#1157
b11101111111 E
b10101010001010000000000000001 F
b0 @
b0 ?
b11110 A
b0 >
b0 =
#1160
0"
#1165
1!
#1167
b11111 I
b11111 D
b101000010000100000000000000001 C
b0 7
b0 9
#1170
0!
#1175
1"
#1177
b1 B
b1 @
b101000010000100000000000000001 ?
b11111 A
b1 >
b1 =
b0 E
b0 F
#1180
0"
#1185
1!
#1187
b10 7
b101000010000100000000000000001 9
b1 ;
b100000 I
b100000 D
b0 C
#1190
0!
#1195
1"
#1197
b10 E
b101000010000100000000000000001 F
b1 H
b0 B
b0 @
b0 ?
b100000 A
b0 >
b0 =
#1200
0"
#1205
1!
#1207
b100001 I
b100001 D
b0 7
b0 9
b0 ;
#1210
0!
#1215
1"
#1217
b100001 A
b0 E
b0 F
b0 H
#1220
0"
#1225
1!
#1227
b100010 I
b100010 D
#1230
0!
#1235
1"
#1237
b100010 A
#1240
0"
#1245
1!
#1247
b100011 I
b100011 D
b101000111010011111111111111111 C
#1250
0!
#1255
1"
#1257
b1 B
b11111111111111111111111111111111 @
b101000111010011111111111111111 ?
b100011 A
b1 >
b10100 =
#1260
0"
#1265
1!
#1267
b10011 7
b101000111010011111111111111111 9
b1 ;
b100100 I
b100100 D
b0 C
#1270
0!
#1275
1"
#1277
b10011 E
b101000111010011111111111111111 F
b1 H
b0 B
b0 @
b0 ?
b100100 A
b0 >
b0 =
#1280
0"
#1285
1!
#1287
b100101 I
b100101 D
b100010010010100100000000000 C
b0 7
b0 9
b0 ;
#1290
0!
#1295
1"
#1297
b100100000000000 @
b100010010010100100000000000 ?
b100101 A
b10011 >
b10 =
b0 E
b0 F
b0 H
#1300
0"
#1305
1!
#1307
b11111111111111111111111111101111 7
b100010010010100100000000000 9
b100110 I
b100110 D
b0 C
#1310
0!
#1315
1"
#1317
b11111111111111111111111111101111 E
b100010010010100100000000000 F
b0 @
b0 ?
b100110 A
b0 >
b0 =
#1320
0"
#1325
1!
#1327
b100111 I
b100111 D
b110101001000001111111111100101 C
b0 7
b0 9
#1330
0!
#1335
1"
#1337
b100 B
b11111111111111111111111111100101 @
b110101001000001111111111100101 ?
b100111 A
b11111111111111111111111111101111 =
b0 E
b0 F
#1340
0"
#1345
1!
#1347
b1100 7
b110101001000001111111111100101 9
b100 ;
b101000 I
b101000 D
b0 C
#1350
0!
#1355
1"
#1357
b110101001000001111111111100101 F
b100 H
b0 B
b0 @
b0 ?
b101000 A
b0 =
#1360
0"
#1365
1!
#1367
b1101 I
b1101 D
1J
b11000100101000000000000 C
b0 7
b0 9
b0 ;
#1370
0!
#1375
1"
#1377
b101000000000000 @
b11000100101000000000000 ?
b1101 A
b10 >
b1100100 =
b0 F
b0 H
#1380
0"
#1385
1!
#1387
b1100110 7
0J
b11000100101000000000000 9
b1110 I
b1110 D
b0 C
#1390
0!
#1395
1"
#1397
b1100110 E
b11000100101000000000000 F
b0 @
b0 ?
b1110 A
b0 >
b0 =
#1400
0"
#1405
1!
#1407
b1111 I
b1111 D
b0 7
b0 9
#1410
0!
#1415
1"
#1417
b1111 A
b0 E
b0 F
#1420
0"
#1425
1!
#1427
b10000 I
b10000 D
#1430
0!
#1435
1"
#1437
b10000 A
#1440
0"
#1445
1!
#1447
b10001 I
b10001 D
b100001010001010000000000000000 C
#1450
0!
#1455
1"
#1457
b10 B
b100001010001010000000000000000 ?
b10001 A
b10011 >
b1100110 =
#1460
0"
#1465
1!
#1467
b1100110 7
b100001010001010000000000000000 9
b10 ;
b10010 I
b10010 D
b100001010001100000000000000001 C
#1470
0!
#1475
1"
#1477
b100001010001010000000000000000 F
b10 H
b1 @
b100001010001100000000000000001 ?
b10010 A
b10010 >
#1480
0"
#1485
1!
#1487
b10011 I
b10011 D
b0 C
b10010 8
b1100111 7
b100001010001100000000000000001 9
#1490
0!
#1495
1"
#1497
b0 B
b0 @
b0 ?
b10011 A
b0 >
b0 =
b10001 G
b100001010001100000000000000001 F
#1500
0"
#1505
1!
#1507
b0 7
b0 9
b0 ;
b10100 I
b10100 D
#1510
0!
#1515
1"
#1517
b0 F
b0 H
b10100 A
#1520
0"
#1525
1!
#1527
b10101 I
b10101 D
#1530
0!
#1535
1"
#1537
b10101 A
#1540
0"
#1545
1!
#1547
b10110 I
b10110 D
b10000110001010100100000000000 C
#1550
0!
#1555
1"
#1557
b100100000000000 @
b10000110001010100100000000000 ?
b10110 A
b10010 >
b10001 =
#1560
0"
#1565
1!
#1567
b10111 I
b10111 D
b0 C
b1 7
b10000110001010100100000000000 9
#1570
0!
#1575
1"
#1577
b0 @
b0 ?
b10111 A
b0 >
b0 =
b1 E
b10000110001010100100000000000 F
#1580
0"
#1585
1!
#1587
b0 7
b0 9
b11000 I
b11000 D
#1590
0!
#1595
1"
#1597
b0 E
b0 F
b11000 A
#1600
0"
#1605
1!
